xbrlreportsindexes/__init__.py
xbrlreportsindexes/cmd_line_util.py
xbrlreportsindexes/py.typed
xbrlreportsindexes/run_db_tasks.py
xbrlreportsindexes/cache/esef_entity-data.pkl
xbrlreportsindexes/cache/esef_entity_other_name-data.pkl
xbrlreportsindexes/cache/esef_filing-data.pkl
xbrlreportsindexes/cache/esef_filing_error-data.pkl
xbrlreportsindexes/cache/esef_filing_lang-data.pkl
xbrlreportsindexes/cache/esef_inferred_filing_language-data.pkl
xbrlreportsindexes/cache/sec_cik_ticker_mapping-data.pkl
xbrlreportsindexes/cache/sec_filer-data.pkl
xbrlreportsindexes/cache/sec_former_names-data.pkl
xbrlreportsindexes/cache/sec_industry-data.pkl
xbrlreportsindexes/cache/sec_industry_level-data.pkl
xbrlreportsindexes/cache/sec_industry_structure-data.pkl
xbrlreportsindexes/cache/sp_companies_ciks-data.pkl
xbrlreportsindexes/core/__init__.py
xbrlreportsindexes/core/arelle_utils.py
xbrlreportsindexes/core/constants.py
xbrlreportsindexes/core/data_utils.py
xbrlreportsindexes/core/db_utils.py
xbrlreportsindexes/core/index_db.py
xbrlreportsindexes/model/__init__.py
xbrlreportsindexes/model/base_model.py
xbrlreportsindexes/model/create_view.py
xbrlreportsindexes/model/esef_index_model.py
xbrlreportsindexes/model/sec_feeds_model.py
xbrlreportsindexes/model/types_mapping.py
xbrl_reports_indexes-0.942.dist-info/LICENSE.md
xbrl_reports_indexes-0.942.dist-info/METADATA
xbrl_reports_indexes-0.942.dist-info/WHEEL
xbrl_reports_indexes-0.942.dist-info/entry_points.txt
xbrl_reports_indexes-0.942.dist-info/top_level.txt
xbrl_reports_indexes-0.942.dist-info/RECORD
