Metadata-Version: 2.1
Name: xbrl-reports-indexes
Version: 0.942
Summary: Creates and updates a database for indexes of ESEF filings and SEC XBRL filings and filers (only filings metadata NOT filings contents)
Author-email: Sherif ElGamal <selgamal@outlook.com>
Maintainer-email: Sherif ElGamal <selgamal@outlook.com>
License: Apache-2.0
Project-URL: Homepage, https://github.com/selgamal/xbrl-reports-indexes
Project-URL: Download, https://github.com/selgamal/xbrl-reports-indexes
Project-URL: Documentation, https://github.com/selgamal/xbrl-reports-indexes
Project-URL: Source, https://github.com/selgamal/xbrl-reports-indexes
Keywords: xbrl,esef,sec,edgar,listing,filings,reports
Platform: linux
Platform: win32
Classifier: Development Status :: 4 - Beta
Classifier: Environment :: Console
Classifier: Operating System :: Microsoft :: Windows
Classifier: Operating System :: POSIX :: Linux
Classifier: Programming Language :: Python :: 3.9
Classifier: Topic :: Database
Classifier: Topic :: Text Processing :: Markup :: XML
Classifier: Topic :: Office/Business :: Financial
Requires-Python: >=3.9
License-File: LICENSE.md
Requires-Dist: sqlalchemy
Requires-Dist: arelle-release
Requires-Dist: pycountry
Requires-Dist: pytz
Provides-Extra: db
Requires-Dist: psycopg2 ; extra == 'db'
Requires-Dist: pymysql ; extra == 'db'
